neon_schemas/__init__.py
neon_schemas-0.1.12.dist-info/WHEEL
neon_schemas-0.1.12.dist-info/METADATA
neon_schemas-0.1.12.dist-info/RECORD
